oasysnow/__init__.py
oasysnow/federated/__init__.py
oasysnow/federated/client/__init__.py
oasysnow/federated/client/filters/__init__.py
oasysnow/federated/client/filters/filter_data.py
oasysnow/federated/client/filters/filter_results.py
oasysnow/federated/client/trainer/__init__.py
oasysnow/federated/client/trainer/trainer.py
oasysnow/federated/common/__init__.py
oasysnow/federated/common/attestation_service/__init__.py
oasysnow/federated/common/attestation_service/server.py
oasysnow/federated/common/attestation_service/verification.py
oasysnow/federated/common/model/__init__.py
oasysnow/federated/common/model/gennet_model.py
oasysnow/federated/common/model/global_model.py
oasysnow/federated/common/model/data/SNP_gene_mask.npz
oasysnow/federated/common/model/data/__init__.py
oasysnow/federated/server/__init__.py
oasysnow/federated/server/filters/__init__.py
oasysnow/federated/server/filters/filter_data.py
oasysnow/federated/server/filters/filter_results.py
oasysnow/federated/server/model_runner/__init__.py
oasysnow/federated/server/model_runner/model_runner.py
test_nvf_builds-0.0.3.19.dist-info/LICENSE
test_nvf_builds-0.0.3.19.dist-info/METADATA
test_nvf_builds-0.0.3.19.dist-info/WHEEL
test_nvf_builds-0.0.3.19.dist-info/top_level.txt
test_nvf_builds-0.0.3.19.dist-info/RECORD
